nauth/__init__.py
nauth/_version.py
nauth/errors.py
nauth/utils.py
nauth/clients/__init__.py
nauth/clients/auth0_client.py
nauth/clients/auth_client.py
nauth/clients/auth_client_factory.py
nauth/clients/uaa_client.py
nauth/tests/__init__.py
nauth/tests/conftest.py
nauth/tests/test_auth0_client.py
nauth/tests/test_auth_factory.py
nauth/tests/test_uaa_client.py
nauth/tests/fixtures/__init__.py
nauth/tests/fixtures/fixtures.py
nauth/tests/fixtures/requests.py
nauth-1.0.12.dist-info/DESCRIPTION.rst
nauth-1.0.12.dist-info/METADATA
nauth-1.0.12.dist-info/RECORD
nauth-1.0.12.dist-info/WHEEL
nauth-1.0.12.dist-info/metadata.json
nauth-1.0.12.dist-info/top_level.txt
