Metadata-Version: 2.0
Name: nauth
Version: 1.0.12
Summary: Nervana platform authorization and authentication related
Home-page: http://www.nervanasys.com
Author: Intel Corporation
Author-email: info@nervanasys.com
License: License :: OSI Approved :: Apache Software License
Platform: UNKNOWN
Classifier: Development Status :: 5 - Production/Stable
Classifier: Environment :: Console
Classifier: Environment :: Console :: Curses
Classifier: Environment :: Web Environment
Classifier: Intended Audience :: End Users/Desktop
Classifier: Intended Audience :: Developers
Classifier: Intended Audience :: Science/Research
Classifier: Operating System :: POSIX
Classifier: Operating System :: MacOS :: MacOS X
Classifier: Operating System :: Microsoft :: Windows
Classifier: Programming Language :: Python
Classifier: Topic :: Software Development :: Libraries :: Python Modules
Classifier: Topic :: Scientific/Engineering :: Artificial Intelligence
Classifier: Topic :: Scientific/Engineering :: Information Analysis
Classifier: Topic :: System :: Distributed Computing
Requires-Dist: requests (==2.13.0)
Requires-Dist: six (>=1.10.0)
